kerashistoryplot/__init__.py
kerashistoryplot/callbacks.py
kerashistoryplot/data.py
kerashistoryplot/plot.py
kerashistoryplot-0.0.10.dist-info/LICENSE
kerashistoryplot-0.0.10.dist-info/METADATA
kerashistoryplot-0.0.10.dist-info/WHEEL
kerashistoryplot-0.0.10.dist-info/entry_points.txt
kerashistoryplot-0.0.10.dist-info/top_level.txt
kerashistoryplot-0.0.10.dist-info/RECORD
