Metadata-Version: 2.1
Name: kerashistoryplot
Version: 0.0.10
Summary: Plot Keras model losses and metrics live in Jupyter
Home-page: https://github.com/ig248/kerashistoryplot
Author: Igor Gotlibovych
Author-email: igor.gotlibovych@gmail.com
License: MIT
Platform: UNKNOWN
Classifier: Intended Audience :: Developers
Classifier: Operating System :: OS Independent
Classifier: Programming Language :: Python
Classifier: Programming Language :: Python :: 3
Classifier: Programming Language :: Python :: 3.6
Provides-Extra: matplotlib
Requires-Dist: matplotlib ; extra == 'matplotlib'
